{
    "006": [
        "УПД1",
        "УПД2",
        "УПД3",
        "УПД4",
        "УПД5",
        "УПД6",
        "УПД13",
        "УПД14",
        "АВЗ1",
        "АВЗ2",
        "АВЗ3",
        "ОЦЛ1"
    ],
    "007": [
        "УПД1",
        "УПД2",
        "УПД3",
        "УПД4",
        "УПД5",
        "УПД6",
        "УПД13",
        "УПД14",
        "ОЦЛ3",
        "ОЦЛ4",
        "УКФ2",
        "УКФ4"
    ],
    "011": [
        "ЗИС19",
        "АУД1",
        "ЗИС32"
    ],
    "015": [
        "УПД1",
        "УПД2",
        "УПД3",
        "УПД4",
        "УПД5",
        "УПД6",
        "УПД13",
        "УПД14"
    ],
    "021": [
        "АУД1",
        "ЗИС26",
        "ЗИС33",
        "ЗИС39"
    ],
    "027": [
        "АВЗ1",
        "АВЗ2",
        "АВЗ3",
        "ЗИС7",
        "ЗИС13",
        "ЗТС2",
        "ЗТС3",
        "ОДТ4",
        "УПД1",
        "УПД5",
        "УПД13"
    ],
    "028": [
        "УПД1",
        "УПД2",
        "УПД3",
        "УПД4",
        "УПД5",
        "УПД6",
        "УПД13",
        "УПД14",
        "ОЦЛ3",
        "ОЦЛ4",
        "УКФ2",
        "УКФ4"
    ],
    "030": [
        "ИАФ4"
    ],
    "031": [
        "УПД1",
        "УПД2",
        "УПД3",
        "УПД4",
        "УПД5",
        "УПД6",
        "УПД13",
        "УПД14"
    ],
    "033": [
        "ОЦЛ3",
        "ОЦЛ4",
        "УКФ2",
        "УКФ4"
    ],
    "034": [
        "ЗИС19",
        "ЗИС35"
    ],
    "036": [
        "ЗИС8",
        "ЗИС17",
        "УПД1",
        "УПД2",
        "УПД3",
        "УПД4",
        "УПД5",
        "УПД6",
        "УПД13",
        "УПД14"
    ],
    "037": [
        "АУД5",
        "ЗИС8",
        "УПД6",
        "УПД14"
    ],
    "041": [
        "АВЗ1",
        "АВЗ2",
        "ЗИС18"
    ],
    "042": [
        "ИАФ1",
        "ИАФ5",
        "ОПО1",
        "ОПО2",
        "УПД1",
        "УПД2",
        "УПД4"
    ],
    "043": [
        "ЗИС34",
        "ОДТ2",
        "ОПО1",
        "ОПО2",
        "СОВ1"
    ],
    "046": [
        "ЗИС19",
        "ЗИС35"
    ],
    "049": [
        "АУД2",
        "ЗИС12",
        "УПД1",
        "ЗИС26"
    ],
    "050": [
        "АВЗ1",
        "АВЗ2",
        "ЗИС7",
        "ЗИС13",
        "ЗТС2",
        "ЗТС3",
        "ОДТ4",
        "УПД1",
        "УПД5",
        "УПД13",
        "ОЦЛ3",
        "ОЦЛ4",
        "УКФ2",
        "УКФ4"
    ],
    "055": [
        "ОПО1",
        "ОПО2",
        "УПД1",
        "УПД2",
        "УПД4",
        "УПД3",
        "УПД5",
        "УПД6",
        "УПД13",
        "УПД14"
    ],
    "056": [
        "АВЗ1",
        "АВЗ3",
        "УКФ1"
    ],
    "057": [
        "ЗИС35"
    ],
    "059": [
        "АУД1",
        "АУД2",
        "АУД5",
        "АУД7",
        "АУД8",
        "ЗИС26",
        "ЗИС27",
        "ЗИС34",
        "ЗИС35",
        "ОДТ1",
        "ОДТ3",
        "СОВ1"
    ],
    "061": [
        "АВЗ1",
        "АВЗ2",
        "АВЗ3",
        "ЗИС7",
        "ЗИС13",
        "ЗТС2",
        "ЗТС3",
        "ОДТ4",
        "УПД1",
        "УПД5",
        "УПД13"
    ],
    "063": [
        "УПД1",
        "УПД2",
        "УПД3",
        "УПД4",
        "УПД5",
        "УПД6",
        "УПД13",
        "УПД14"
    ],
    "064": [
        "АУД1",
        "АУД2",
        "АУД5",
        "АУД7",
        "АУД8",
        "ЗИС26",
        "ЗИС27",
        "ЗИС34",
        "ЗИС35",
        "ОДТ1",
        "ОДТ3",
        "СОВ1"
    ],
    "067": [
        "УПД1",
        "УПД2",
        "УПД3",
        "УПД4",
        "УПД5",
        "УПД6",
        "УПД13",
        "УПД14",
        "АВЗ1",
        "АВЗ2",
        "АВЗ3",
        "АУД1",
        "ЗИС31",
        "ЗТС1",
        "ЗТС2",
        "ЗТС3",
        "ОПО1",
        "ОПО2",
        "ОПС1",
        "ОЦЛ1",
        "УПД11"
    ],
    "068": [
        "УПД6",
        "ОПО1",
        "ОПО2",
        "УПД1",
        "УПД2",
        "УПД4"
    ],
    "069": [
        "ОЦЛ3",
        "ОЦЛ4",
        "УКФ2",
        "УКФ4",
        "УПД1"
    ],
    "070": [
        "АВЗ1",
        "АВЗ2",
        "АВЗ3",
        "ЗИС7",
        "ЗИС13",
        "ЗТС2",
        "ЗТС3",
        "ОДТ4",
        "УПД1",
        "УПД5",
        "УПД13",
        "ОЦЛ1",
        "УПД3"
    ],
    "073": [
        "УПД1",
        "УПД2",
        "УПД3",
        "УПД4",
        "УПД5",
        "УПД6",
        "УПД13",
        "УПД14",
        "АВЗ1",
        "АВЗ2",
        "АУД5",
        "ЗИС2",
        "ЗИС35"
    ],
    "075": [
        "ЗИС17",
        "ЗИС19",
        "ИАФ7",
        "АУД5",
        "ЗИС8",
        "УПД6",
        "УПД14"
    ],
    "078": [
        "АУД2",
        "ЗИС35",
        "ИАФ1",
        "УПД6"
    ],
    "080": [
        "ЗИС2",
        "ЗИС19",
        "ЗТС2",
        "ЗТС3",
        "АУД2",
        "ЗИС35",
        "ИАФ1",
        "УПД6"
    ],
    "083": [
        "АУД2",
        "ЗИС35",
        "ИАФ1",
        "УПД6"
    ],
    "084": [
        "АВЗ1",
        "АВЗ3",
        "УКФ1",
        "АУД5",
        "ЗИС8",
        "УПД6",
        "УПД14"
    ],
    "085": [
        "АУД5",
        "ЗИС8",
        "УПД6",
        "УПД14",
        "АУД2",
        "ЗИС35",
        "ИАФ1"
    ],
    "086": [
        "УПД1",
        "УПД2",
        "УПД3",
        "УПД4",
        "УПД5",
        "УПД6",
        "УПД13",
        "УПД14",
        "АУД5",
        "АУД2",
        "ЗИС35",
        "ИАФ1"
    ],
    "088": [
        "УПД1",
        "УПД2",
        "УПД3",
        "УПД4",
        "УПД5",
        "УПД6",
        "УПД13",
        "УПД14",
        "АУД5",
        "ЗИС8",
        "АУД2",
        "ЗИС35",
        "ИАФ1"
    ],
    "089": [
        "АУД2",
        "ЗИС35",
        "ИАФ1",
        "УПД6",
        "УПД1",
        "УПД2",
        "УПД3",
        "УПД4",
        "УПД5",
        "УПД13",
        "УПД14",
        "АУД5",
        "ЗИС8"
    ],
    "090": [
        "УПД1",
        "УПД2",
        "УПД3",
        "УПД4",
        "УПД5",
        "УПД6",
        "УПД13",
        "УПД14",
        "АУД5",
        "ЗИС8",
        "АУД2",
        "ЗИС35",
        "ИАФ1"
    ],
    "091": [
        "УПД1", 
        "УПД2", 
        "УПД3", 
        "УПД4",
        "УПД5",
        "УПД6",
        "УПД13",
        "УПД14",
        "АУД2",
        "АУД5",
        "ЗИС8",
        "АВЗ1",
        "АВЗ2",
        "АВЗ3", 
        "ЗИС7", 
        "ЗИС13",
        "ЗИС35",
        "ЗТС2", 
        "ЗТС3", 
        "ОДТ4",
        "ИАФ1"
    ],
    "094": [
        "УПД6",
        "АУД2",
        "ЗИС35",
        "ИАФ1",
        "УПД1",
        "УПД2",
        "УПД3",
        "УПД4",
        "УПД5",
        "УПД6",
        "УПД13",
        "УПД14",
        "АУД5",
        "ЗИС8",
        "АВЗ1",
        "АВЗ2",
        "АВЗ3",
        "ОЦЛ1"
    ],
    "096": [
        "АУД5",
        "ЗИС8",
        "ЗИС35",
        "СОВ1",
        "УПД1",
        "УПД2",
        "УПД3",
        "УПД4",
        "УПД5",
        "УПД6",
        "УПД13",
        "УПД14"
    ],
    "098": [
        "АУД5",
        "ЗИС8",
        "ЗИС35",
        "СОВ1",
        "УПД1",
        "УПД2",
        "УПД3",
        "УПД4",
        "УПД5",
        "УПД6",
        "УПД13",
        "УПД14"
    ],
    "100": [
        "УПД6",
        "АУД2",
        "ЗИС35",
        "ИАФ1",
        "УПД1",
        "УПД2",
        "УПД3",
        "УПД4",
        "УПД5",
        "УПД6",
        "УПД13",
        "УПД14"
    ],
    "101": [
        "УПД1",
        "УПД2",
        "УПД3",
        "УПД4",
        "УПД5",
        "УПД6",
        "УПД13",
        "УПД14",
        "АУД2",
        "ЗИС35",
        "ИАФ1"
    ],
    "102": [
        "УПД1",
        "УПД2",
        "УПД3",
        "УПД4",
        "УПД5",
        "УПД6",
        "УПД13",
        "УПД14",
        "АУД2",
        "АУД5",
        "ЗИС8",
        "ЗИС35",
        "ИАФ1"
    ],
    "103": [
        "УПД1",
        "УПД2",
        "УПД3",
        "УПД4",
        "УПД5",
        "УПД6",
        "УПД13",
        "УПД14",
        "АУД2",
        "АУД5",
        "ЗИС8",
        "ЗИС35",
        "ИАФ1"
    ],
    "104": [
        "УПД6",
        "УПД14",
        "АУД5",
        "ЗИС2",
        "ЗИС8",
        "ЗИС19",
        "АВЗ1"
    ],
    "105": [
        "УПД1",
        "УПД5",
        "УПД6",
        "УПД13",
        "УПД14",
        "АУД1",
        "АУД5",
        "ЗИС7",
        "ЗИС8",
        "ЗИС13",
        "ЗИС14",
        "ЗИС26",
        "ЗИС33",
        "ЗИС39",
        "ЗТС2",
        "ЗТС3",
        "ОДТ4",
        "АВЗ1",
        "АВЗ2",
        "АВЗ3"
    ],
    "107": [
        "УПД1",
        "УПД2",
        "УПД3",
        "УПД4",
        "УПД5",
        "УПД6",
        "УПД13",
        "УПД14",
        "АУД5",
        "ЗИС8",
        "ЗИС35",
        "СОВ1"
    ],
    "109": [
        "УПД1",
        "УПД2",
        "УПД3",
        "УПД4",
        "УПД5",
        "УПД6",
        "УПД13",
        "УПД14",
        "АВЗ1",
        "АВЗ2",
        "АВЗ3",
        "ЗИС8",
        "ЗИС14",
        "ЗИС35",
        "ОЦЛ1",
        "АУД5",
        "СОВ1"
    ],
    "111": [
        "УПД1",
        "УПД2",
        "УПД3",
        "УПД4",
        "УПД5",
        "УПД6",
        "УПД13",
        "УПД14",
        "АУД5",
        "ЗИС8",
        "ЗИС35",
        "СОВ1"
    ],
    "112": [
        "УПД1",
        "УПД2",
        "УПД3",
        "УПД4",
        "УПД5",
        "УПД6",
        "УПД13",
        "УПД14",
        "АУД5",
        "ЗИС8",
        "ЗИС35",
        "СОВ1",
        "АВЗ1",
        "АВЗ2",
        "АВЗ3",
        "ОЦЛ1"
    ],
    "113": [
        "УПД1",
        "УПД2",
        "УПД3",
        "УПД4",
        "УПД5",
        "УПД6",
        "УПД13",
        "УПД14",
        "АУД5",
        "ЗИС8",
        "ЗИС35",
        "СОВ1",
        "АВЗ1",
        "АВЗ2",
        "АВЗ3",
        "ОЦЛ1",
        "УПД3"
    ],
    "115": [
        "УПД1",
        "УПД2",
        "УПД3",
        "УПД4",
        "УПД5",
        "УПД6",
        "УПД13",
        "УПД14",
        "АУД5",
        "ЗИС8",
        "ЗИС35",
        "СОВ1",
        "АВЗ1",
        "АВЗ2",
        "АВЗ3",
        "ЗИС14",
        "ОЦЛ1",
        "ОЦЛ3",
        "ОЦЛ4",
        "УКФ2",
        "УКФ4"
    ],
    "116": [
        "УПД1",
        "УПД2",
        "УПД3",
        "УПД4",
        "УПД5",
        "УПД6",
        "УПД13",
        "УПД14",
        "АУД5",
        "ЗИС8",
        "ЗИС35",
        "АВЗ1",
        "ЗИС2",
        "ЗИС19",
        "СОВ1",
        "АВЗ2",
        "АВЗ3",
        "ОЦЛ1"
    ],
    "117": [
        "УПД1",
        "УПД2",
        "УПД3",
        "УПД4",
        "УПД5",
        "УПД6",
        "АУД5",
        "ЗИС8",
        "ЗИС35",
        "УПД13",
        "УПД14",
        "ЗИС14",
        "СОВ1",
        "ОЦЛ1",
        "АВЗ1",
        "ЗИС2",
        "ЗИС19"
    ],
    "118": [
        "УПД1",
        "УПД2",
        "УПД3",
        "УПД4",
        "АУД5",
        "ЗИС8",
        "ЗИС35",
        "АВЗ1",
        "ЗИС2",
        "ЗИС19",
        "УПД5",
        "УПД6",
        "УПД13",
        "УПД14",
        "СОВ1",
        "ЗИС14",
        "ОЦЛ1"
    ],
    "122": [
        "АВЗ1",
        "ЗИС2",
        "ЗИС19",
        "УПД1",
        "УПД2",
        "УПД3",
        "УПД4",
        "УПД5",
        "УПД6",
        "УПД13",
        "УПД14",
        "АУД5",
        "ЗИС8",
        "ЗИС35",
        "СОВ1",
        "ОЦЛ1",
        "АВЗ2",
        "АВЗ3",
        "ЗИС7",
        "ЗИС13",
        "ЗТС2",
        "ЗТС3",
        "ОДТ4"
    ],
    "124": [
        "АВЗ1",
        "ЗИС2",
        "ЗИС19",
        "УПД1",
        "УПД2",
        "УПД3",
        "УПД4",
        "УПД5",
        "УПД6",
        "УПД13",
        "УПД14",
        "АУД5",
        "ЗИС8",
        "ЗИС35",
        "СОВ1",
        "АВЗ2",
        "ОЦЛ1",
        "АВЗ3",
        "ЗИС7",
        "ЗИС13",
        "ЗТС2",
        "ЗТС3",
        "ОДТ4"
    ],
    "125": [
        "ЗТС2",
        "ЗТС3",
        "ОЦЛ1",
        "АВЗ1",
        "ЗИС2",
        "ЗИС19"
    ],
    "126": [
        "ЗТС2",
        "ЗТС3",
        "ОЦЛ1",
        "АВЗ1",
        "ЗИС2",
        "ЗИС19"
    ],
    "127": [
        "АВЗ1",
        "АВЗ2",
        "АВЗ3",
        "ЗИС7",
        "ЗИС13",
        "ЗТС2",
        "ЗТС3",
        "ОДТ4",
        "УПД1",
        "УПД5",
        "УПД13",
        "ЗИС17",
        "ЗИС19",
        "ИАФ7"
    ],
    "128": [
        "ИАФ1",
        "ИАФ5",
        "ОПО1",
        "ОПО2",
        "УПД1",
        "УПД2",
        "УПД4"
    ],
    "130": [
        "ЗИС17",
        "ЗИС19",
        "ИАФ7",
        "ИАФ1",
        "ИАФ5",
        "ОПО1",
        "ОПО2",
        "УПД1",
        "УПД2",
        "УПД4",
        "УПД3",
        "УПД5",
        "УПД6",
        "УПД13",
        "УПД14",
        "АВЗ1",
        "АВЗ2",
        "АВЗ3",
        "ЗИС7",
        "ЗИС13",
        "ЗТС2",
        "ЗТС3",
        "ОДТ4"
    ],
    "131": [
        "ЗИС3",
        "ЗИС12",
        "ЗИС19",
        "ЗИС20",
        "ЗИС27",
        "ЗИС35",
        "ИАФ1",
        "ИНЦ1",
        "ИНЦ2",
        "ИНЦ3",
        "ИНЦ4",
        "ИНЦ5",
        "ИНЦ6",
        "ОДТ7",
        "УКФ3",
        "УПД0",
        "УПД1",
        "УПД2",
        "УПД4",
        "УПД5",
        "УПД6",
        "УПД7",
        "УПД8",
        "УПД9",
        "УПД10",
        "УПД11",
        "УПД12",
        "УПД13",
        "УПД14"
    ],
    "132": [
        "ОЦЛ3",
        "ОЦЛ4",
        "УКФ2",
        "УКФ4",
        "ЗИС2",
        "УКФ1",
        "АУД5",
        "ЗИС8",
        "ЗИС35",
        "СОВ1"
    ],
    "133": [
        "АВЗ1",
        "ЗИС17",
        "ЗИС22",
        "ЗИС35",
        "ИАФ5",
        "УКФ1",
        "УПД1",
        "УПД14",
        "АУД5",
        "ЗИС8",
        "УПД6",
        "ИАФ1",
        "ОПО1",
        "ОПО2",
        "УПД2",
        "УПД4",
        "АУД2",
        "ИПО1",
        "ИПО2",
        "ИПО3",
        "ИПО4"
    ],
    "135": [
        "АВЗ1",
        "ЗИС17",
        "ЗИС22",
        "ЗИС35",
        "ИАФ5",
        "УКФ1",
        "УПД1",
        "УПД14",
        "АУД5",
        "ЗИС8",
        "УПД6",
        "ИАФ1",
        "ИАФ5",
        "ОПО1",
        "ОПО2",
        "УПД2",
        "УПД4",
        "АУД2",
        "ЗИС35",
        "УПД6",
        "ИПО1",
        "ИПО2",
        "ИПО3",
        "ИПО4",
        "АУД1",
        "АУД5",
        "АУД7",
        "АУД8",
        "ЗИС26",
        "ЗИС27",
        "ЗИС34",
        "ОДТ1",
        "ОДТ3",
        "СОВ1"
    ],
    "136": [
        "АУД1",
        "АУД2",
        "АУД5",
        "АУД7",
        "АУД8",
        "ЗИС26",
        "ЗИС27",
        "ЗИС34",
        "ЗИС35",
        "ОДТ1",
        "ОДТ3",
        "СОВ1",
        "ЗИС4",
        "ЗИС17",
        "ЗИС33",
        "ЗИС39",
        "ИАФ7",
        "ОЦЛ2",
        "УКФ4",
        "УПД1",
        "УПД2",
        "УПД4",
        "УПД12",
        "АУД4"
    ],
    "137": [
        "АУД1",
        "АУД2",
        "АУД5",
        "АУД7",
        "АУД8",
        "ЗИС26",
        "ЗИС27",
        "ЗИС34",
        "ЗИС35",
        "ОДТ1",
        "ОДТ3",
        "СОВ1",
        "ЗИС33",
        "ЗИС39",
        "АВЗ1",
        "АВЗ2",
        "ЗИС2"
    ],
    "138": [
        "АУД1",
        "ЗИС32",
        "АВЗ1",
        "ЗИС2",
        "ЗИС19"
    ],
    "139": [
        "АУД5",
        "ЗИС8",
        "УПД6",
        "УПД14"
    ],
    "140": [
        "АВЗ1",
        "АВЗ2",
        "АВЗ3",
        "ЗТС2",
        "ЗТС3",
        "ИАФ1",
        "ИАФ5",
        "ОПО1",
        "ОПО2",
        "ОПС1",
        "УПД1",
        "АУД2"
    ],
    "141": [
        "АУД1",
        "ЗИС26",
        "ЗИС33",
        "ЗИС39",
        "АУД2",
        "АУД5",
        "АУД7",
        "АУД8",
        "ЗИС26",
        "ЗИС27",
        "ЗИС34",
        "ЗИС35",
        "ОДТ1",
        "ОДТ3",
        "СОВ1"
    ],
    "142": [
        "АУД1",
        "ЗИС26",
        "ЗИС33",
        "ЗИС39",
        "АУД2",
        "АУД5",
        "АУД7",
        "АУД8",
        "ЗИС27",
        "ЗИС34",
        "ЗИС35",
        "ОДТ1",
        "ОДТ3",
        "СОВ1",
        "АУД2",
        "ЗИС3",
        "ЗИС19",
        "ЗИС20",
        "ИАФ0",
        "ИАФ1",
        "ИАФ2",
        "ИАФ3",
        "ИАФ4",
        "ИАФ5",
        "ИАФ6",
        "ИАФ7",
        "ИНЦ0",
        "ИНЦ1",
        "ИНЦ2",
        "ИНЦ3",
        "ИНЦ4",
        "ИНЦ5",
        "ИНЦ6",
        "ОДТ7",
        "УПД0",
        "УПД1",
        "УПД2",
        "УПД4",
        "УПД5",
        "УПД6",
        "УПД7",
        "УПД8",
        "УПД9",
        "УПД10",
        "УПД11",
        "УПД12",
        "УПД13",
        "УПД14"
    ],
    "143": [
        "АВЗ1",
        "АВЗ2",
        "АВЗ3",
        "ЗИС14",
        "ОЦЛ1",
        "УПД3",
        "ЗНИ5",
        "ЗНИ6",
        "ЗНИ7",
        "ОЦЛ3",
        "ОЦЛ4",
        "УКФ2",
        "УКФ4"
    ],
    "145": [
        "ЗИС26",
        "ЗИС27",
        "ЗИС28",
        "ЗИС29",
        "ЗИС31",
        "ЗИС35",
        "УКФ0",
        "УКФ1",
        "АВЗ1",
        "АВЗ2",
        "ЗИС18",
        "ЗИС19",
        "ЗИС2",
        "СОВ1"
    ],
    "148": [
        "АУД5",
        "ЗИС8",
        "ЗИС35",
        "СОВ1",
        "УПД1",
        "УПД2",
        "УПД3",
        "УПД4",
        "УПД5",
        "УПД6",
        "УПД13",
        "УПД14",
        "АУД1",
        "ЗИС26",
        "ЗИС33",
        "ЗИС39"
    ],
    "149": [
        "АВЗ1",
        "АВЗ2",
        "АВЗ3",
        "ЗИС7",
        "ЗИС13",
        "ЗИС14",
        "ЗТС2",
        "ЗТС3",
        "ОДТ4",
        "УПД1",
        "УПД5",
        "УПД13",
        "ЗИС34",
        "ОДТ2",
        "ОПО1",
        "ОПО2",
        "СОВ1",
        "УПД6",
        "АУД5",
        "ЗИС8",
        "ЗИС35",
        "СОВ1"
    ],
    "152": [
        "УПД1",
        "УПД2",
        "УПД3",
        "УПД4",
        "УПД5",
        "УПД6",
        "УПД13",
        "УПД14",
        "АУД5",
        "ЗИС8",
        "ИАФ1",
        "ИАФ5",
        "ОПО1",
        "ОПО2"
    ],
    "153": [
        "АВЗ1",
        "АВЗ2",
        "АВЗ3",
        "ЗИС14",
        "ОЦЛ1",
        "УПД3",
        "ЗИС2",
        "УКФ1"
    ],
    "155": [
        "ИНЦ4",
        "ИПО1",
        "ИПО2",
        "ИПО3",
        "ИПО4",
        "АВЗ1",
        "АВЗ2",
        "АВЗ3",
        "ЗТС2",
        "ЗТС3",
        "ИАФ1",
        "ИАФ5",
        "ОПО1",
        "ОПО2",
        "ОПС1",
        "УПД1"
    ],
    "157": [
        "ЗТС2",
        "ЗТС3",
        "ОЦЛ1",
        "ЗНИ1",
        "ЗНИ2",
        "ЗНИ3",
        "ЗНИ4",
        "ЗНИ8",
        "ЗТС5",
        "АВЗ1",
        "АВЗ2",
        "АВЗ3",
        "АУД1",
        "ЗИС31",
        "ЗТС1",
        "ОПО1",
        "ОПО2",
        "ОПС1",
        "ОЦЛ1",
        "УПД1",
        "УПД11"
    ],
    "159": [
        "ОЦЛ3",
        "ОЦЛ4",
        "УКФ2",
        "УКФ4",
        "АУД2",
        "ЗИС35",
        "ИАФ1",
        "УПД6",
        "ОПО1",
        "ОПО2",
        "УПД1",
        "УПД2",
        "УПД4",
        "АВЗ1",
        "АВЗ2",
        "АВЗ3",
        "ЗТС2",
        "ЗТС3",
        "ИАФ1",
        "ИАФ5",
        "ОПО1",
        "ОПО2",
        "ОПС1",
        "АУД1",
        "ЗИС31",
        "ЗТС1",
        "ОЦЛ1",
        "УПД11"
    ],
    "160": [
        "ЗНИ1",
        "ЗНИ2",
        "ЗНИ3",
        "ЗНИ4",
        "ЗНИ8",
        "ЗТС2",
        "ЗТС3",
        "ОЦЛ1",
        "ЗТС5"
    ],
    "163": [
        "ЗНИ1",
        "ЗНИ2",
        "ЗНИ3",
        "ЗНИ4",
        "ЗНИ8",
        "УПД1",
        "УПД2",
        "УПД3",
        "УПД4",
        "УПД5",
        "УПД6",
        "УПД13",
        "УПД14",
        "ОПО1",
        "ОПО2",
        "ИАФ1",
        "ИАФ5",
        "АУД2",
        "ЗИС35",
        "АВЗ3",
        "ЗИС2",
        "ЗИС19"
    ],
    "164": [
        "ЗИС34",
        "ОДТ2",
        "ОПО1",
        "ОПО2",
        "СОВ1",
        "УПД6",
        "АВЗ1",
        "АВЗ2",
        "АВЗ3",
        "ЗИС7",
        "ЗИС14",
        "ЗТС2",
        "ЗТС3",
        "ОДТ4",
        "УПД1",
        "УПД5",
        "УПД13"
    ],
    "165": [
        "ОПО1",
        "ОПО2",
        "УПД1",
        "УПД2",
        "УПД4",
        "АУД2",
        "АУД4"
    ],
    "166": [
        "АВЗ1",
        "АВЗ2",
        "АВЗ3",
        "ЗИС7",
        "ЗИС13",
        "ЗТС2",
        "ЗТС3",
        "ОДТ4",
        "УПД1",
        "УПД5",
        "УПД13",
        "ЗИС19",
        "ЗИС35"
    ],
    "167": [
        "АВЗ1",
        "АВЗ2",
        "ЗНИ5",
        "ЗНИ6",
        "ЗНИ7",
        "ЗИС18"
    ],
    "168": [
        "АУД2",
        "ЗИС35",
        "ИАФ1",
        "УПД6",
        "УПД1",
        "УПД2",
        "УПД3",
        "УПД4",
        "УПД5",
        "УПД6",
        "УПД13",
        "УПД14",
        "ОПО1",
        "ОПО2"
    ],
    "171": [
        "АВЗ1",
        "АВЗ2",
        "УПД13"
    ],
    "174": [
        "АВЗ1",
        "АВЗ2",
        "ЗИС18",
        "ЗИС27"
    ],
    "175": [
        "АВЗ1",
        "АВЗ2",
        "АВЗ3",
        "ЗИС7",
        "ЗИС17",
        "ЗИС18",
        "ИПО1",
        "ИПО2",
        "ИПО3",
        "ИПО4",
        "ЗИС15",
        "ОЦЛ4"
    ],
    "177": [
        "ОЦЛ3",
        "ОЦЛ4",
        "УКФ2",
        "УКФ4"
    ],
    "178": [
        "АУД2",
        "ЗИС35",
        "ИАФ1",
        "УПД6",
        "ОПО1",
        "ОПО2",
        "УПД1",
        "УПД2",
        "УПД4"
    ],
    "179": [
        "ЗНИ1",
        "ЗНИ2",
        "ЗНИ3",
        "ЗНИ4",
        "ЗНИ8",
        "ИАФ1",
        "ИАФ5",
        "ОПО1",
        "ОПО2",
        "УПД1",
        "УПД2",
        "УПД4"
    ],
    "180": [
        "ИАФ1",
        "ИАФ5",
        "ОПО1",
        "ОПО2",
        "УПД1",
        "УПД2",
        "УПД4"
    ],
    "181": [
        "ЗИС17",
        "ЗИС19",
        "ИАФ7"
    ],
    "183": [
        "АВЗ1",
        "АВЗ2",
        "УПД13",
        "ОПО1",
        "ОПО2",
        "УПД1",
        "УПД2",
        "УПД4"
    ],
    "188": [
        "АВЗ1",
        "АВЗ2",
        "АУД5",
        "ЗИС2",
        "ЗИС35"
    ],
    "189": [
        "АУД5",
        "ЗИС8",
        "ЗИС35",
        "СОВ1"
    ],
    "190": [
        "АВЗ1",
        "АВЗ2",
        "ЗИС18"
    ],
    "191": [
        "АВЗ1",
        "АВЗ2",
        "АВЗ3",
        "ЗИС14",
        "ОЦЛ1",
        "УПД3"
    ],
    "192": [
        "АУД5",
        "ЗИС8",
        "ЗИС35",
        "СОВ1"
    ],
    "193": [
        "АВЗ1",
        "АВЗ2",
        "АВЗ3",
        "ЗИС7",
        "ЗИС13",
        "ЗТС2",
        "ЗТС3",
        "ОДТ4",
        "ОПС1",
        "ОПС2"
    ],
    "194": [
        "ЗИС8",
        "ЗИС17"
    ],
    "195": [
        "АВЗ1",
        "АВЗ2",
        "АВЗ3",
        "ОЦЛ1",
        "УПД3",
        "УПД13"
    ],
    "196": [
        "АУД5",
        "ЗИС8",
        "ЗИС35",
        "СОВ1",
        "ЗИС17"
    ],
    "198": [
        "УПД1",
        "ИАФ1",
        "ИАФ5",
        "ОПО1",
        "ОПО2",
        "УПД2",
        "УПД4",
        "УПД5",
        "УПД6",
        "УПД13",
        "УПД14"
    ],
    "201": [
        "АУД5",
        "ЗИС8",
        "УПД6",
        "УПД14",
        "ЗИС35",
        "СОВ1"
    ],
    "202": [
        "ЗИС8",
        "ЗИС17",
        "АУД5",
        "ЗИС35",
        "СОВ1"
    ],
    "203": [
        "АВЗ1",
        "АВЗ2",
        "АВЗ3",
        "АВЗ4",
        "АВЗ5",
        "ЗИС7",
        "ЗИС26",
        "ОПО1",
        "ОПО2",
        "ОПО3",
        "ОПО4",
        "ОПС1",
        "ОПС2",
        "УКФ3",
        "УКФ4"
    ],
    "204": [
        "АВЗ1",
        "АВЗ2",
        "УПД13"
    ],
    "207": [
        "АУД2",
        "ЗИС12",
        "УПД1",
        "АВЗ1",
        "АВЗ2",
        "УПД13"
    ],
    "210": [
        "АВЗ1",
        "АВЗ2",
        "АВЗ3",
        "АВЗ4",
        "АВЗ5",
        "ЗИС7",
        "ЗИС26",
        "ОПО1",
        "ОПО2",
        "ОПО3",
        "ОПО4",
        "ОПС1",
        "ОПС2",
        "УКФ3",
        "УКФ4"
    ],
    "212": [
        "АУД5",
        "ЗИС8",
        "ЗИС35",
        "СОВ1",
        "УПД1",
        "УПД2",
        "УПД3",
        "УПД4",
        "УПД5",
        "УПД6",
        "УПД13",
        "УПД14"
    ],
    "213": [
        "УПД1",
        "УПД2",
        "УПД3",
        "УПД4",
        "УПД5",
        "УПД6",
        "УПД13",
        "УПД14"
    ],
    "214": [
        "АУД5",
        "ЗИС8",
        "ЗИС35",
        "СОВ1",
        "АУД1",
        "ЗИС26",
        "ЗИС33",
        "ЗИС39",
        "АВЗ1",
        "АВЗ2",
        "АВЗ3",
        "АВЗ4",
        "АВЗ5",
        "ЗИС7",
        "ОПО1",
        "ОПО2",
        "ОПО3",
        "ОПО4",
        "ОПС1",
        "ОПС2",
        "УКФ3",
        "УКФ4",
        "АУД2"
    ],
    "215": [
        "АВЗ1",
        "АВЗ3",
        "ЗИС7",
        "ЗИС17",
        "ЗИС18",
        "ЗИС23",
        "ИПО1",
        "ИПО2",
        "ИПО3",
        "ИПО4",
        "АВЗ2",
        "ЗИС15",
        "ОЦЛ4"
    ],
    "217": [
        "АВЗ1",
        "АВЗ2",
        "АВЗ3",
        "АВЗ4",
        "ЗИС7",
        "ЗИС26",
        "ОПО1",
        "ОПО2",
        "ОПО3",
        "ОПО4",
        "ОПС1",
        "ОПС2",
        "УКФ3",
        "УКФ4",
        "АВЗ5"
    ],
    "218": [
        "УПД1",
        "УПД2",
        "УПД3",
        "УПД4",
        "УПД5",
        "УПД6",
        "УПД13",
        "УПД14",
        "ОПО1",
        "ОПО2"
    ],
    "219": [
        "УПД1",
        "УПД2",
        "УПД3",
        "УПД4",
        "УПД5",
        "УПД6",
        "УПД13",
        "УПД14",
        "ОПО1",
        "ОПО2",
        "АУД2",
        "ЗИС35",
        "ИАФ1"
    ],
    "221": [
        "АУД2",
        "ОЦЛ3",
        "УКФ4"
    ],
    "222": [
        "УПД3",
        "УПД4",
        "УПД5",
        "УПД6",
        "УПД13",
        "УПД14",
        "ОПО1",
        "ОПО2",
        "УПД1",
        "УПД2",
        "АУД2",
        "ЗИС35",
        "ИАФ1"
    ]
}